Metadata-Version: 1.0
Name: chin-distributions-udacity
Version: 0.2
Summary: Gaussian and Binomial distributions
Home-page: UNKNOWN
Author: Chinmay Kumar
Author-email: chinmaykumar2001@gmail.com
License: UNKNOWN
Platform: UNKNOWN
